curve_fit_py/__init__.py
curve_fit_py/curve_fit_py.py
curve_fit_py-1.4.dist-info/LICENSE.txt
curve_fit_py-1.4.dist-info/METADATA
curve_fit_py-1.4.dist-info/WHEEL
curve_fit_py-1.4.dist-info/top_level.txt
curve_fit_py-1.4.dist-info/RECORD
