Metadata-Version: 2.1
Name: curve_fit_py
Version: 1.4
Summary: A package for fitting a curve given an array of data points
Home-page: 
Author: Giovanni Paiela
Author-email: jovpa47@gmail.com
License: MIT
Project-URL: Source, https://github.com/Paiela/curve_fit_py
Classifier: Development Status :: 5 - Production/Stable
Classifier: Intended Audience :: Education
Classifier: Programming Language :: Python :: 3.11
Classifier: Topic :: Scientific/Engineering :: Mathematics
Requires-Python: >= 3.11.4
License-File: LICENSE.txt
Requires-Dist: numpy
